admin_honeypot/__init__.py
admin_honeypot/admin.py
admin_honeypot/apps.py
admin_honeypot/forms.py
admin_honeypot/listeners.py
admin_honeypot/models.py
admin_honeypot/signals.py
admin_honeypot/urls.py
admin_honeypot/views.py
admin_honeypot/fake_fs/.dockerenv
admin_honeypot/fake_fs/etc/passwd
admin_honeypot/fake_fs/etc/shadow
admin_honeypot/fake_fs/etc/apt/apt.conf.d/docker-apt-speedup
admin_honeypot/fake_fs/etc/apt/apt.conf.d/docker-autoremove-suggests
admin_honeypot/fake_fs/etc/apt/apt.conf.d/docker-clean
admin_honeypot/fake_fs/etc/apt/apt.conf.d/docker-gzip-indexes
admin_honeypot/fake_fs/etc/apt/apt.conf.d/docker-no-languages
admin_honeypot/fakedb/users.csv
admin_honeypot/locale/es_ES/LC_MESSAGES/django.mo
admin_honeypot/locale/es_ES/LC_MESSAGES/django.po
admin_honeypot/locale/ru/LC_MESSAGES/django.mo
admin_honeypot/locale/ru/LC_MESSAGES/django.po
admin_honeypot/locale/zh_CN/LC_MESSAGES/django.mo
admin_honeypot/locale/zh_CN/LC_MESSAGES/django.po
admin_honeypot/locale/zh_Hans/LC_MESSAGES/django.mo
admin_honeypot/locale/zh_Hans/LC_MESSAGES/django.po
admin_honeypot/migrations/0001_initial.py
admin_honeypot/migrations/0002_auto_20160208_0854.py
admin_honeypot/migrations/0003_hashcashmetadata.py
admin_honeypot/migrations/0004_hashcashmetadata_bits_hashcashmetadata_salt_and_more.py
admin_honeypot/migrations/0005_alter_hashcashmetadata_bits_and_more.py
admin_honeypot/migrations/0006_preferences_alter_loginattempt_hashcash_stamp.py
admin_honeypot/migrations/0007_auto_20220516_1501.py
admin_honeypot/migrations/0008_fakeuser.py
admin_honeypot/migrations/0009_alter_fakeuser_id.py
admin_honeypot/migrations/0010_alter_loginattempt_hashcash_stamp.py
admin_honeypot/migrations/0011_alter_loginattempt_hashcash_stamp.py
admin_honeypot/migrations/__init__.py
admin_honeypot/templates/admin_honeypot/404.html
admin_honeypot/templates/admin_honeypot/email_message.txt
admin_honeypot/templates/admin_honeypot/email_subject.txt
admin_honeypot/templates/admin_honeypot/login.html
django_admin_honeypot_advanced-1.0.1.dist-info/LICENSE
django_admin_honeypot_advanced-1.0.1.dist-info/METADATA
django_admin_honeypot_advanced-1.0.1.dist-info/WHEEL
django_admin_honeypot_advanced-1.0.1.dist-info/top_level.txt
django_admin_honeypot_advanced-1.0.1.dist-info/RECORD
