Metadata-Version: 2.1
Name: django-admin-honeypot-advanced
Version: 1.0.1
Summary: An advanced honeypot for Django
Home-page: https://github.com/danielesalimonti/django-admin-honeypot-advanced
Maintainer: Daniele Salimonti
Maintainer-email: danielesalim@outlook.it
License: MIT License
Keywords: django admin honeypot trap hashcash sqli
Classifier: Development Status :: 5 - Production/Stable
Classifier: Framework :: Django
Classifier: Framework :: Django :: 2.2
Classifier: Framework :: Django :: 3.0
Classifier: Intended Audience :: Developers
Classifier: License :: OSI Approved :: MIT License
Classifier: Natural Language :: English
Classifier: Operating System :: OS Independent
Classifier: Programming Language :: Python
Classifier: Programming Language :: Python :: 3
Classifier: Programming Language :: Python :: 3.5
Classifier: Programming Language :: Python :: 3.6
Classifier: Programming Language :: Python :: 3.7
Classifier: Programming Language :: Python :: 3.8
Classifier: Topic :: Internet :: WWW/HTTP :: Dynamic Content
License-File: LICENSE
